lime/__init__.py
lime/config.py
lime/load_config.py
lime/main.py
orchard_lime-0.1.0.dist-info/LICENSE
orchard_lime-0.1.0.dist-info/METADATA
orchard_lime-0.1.0.dist-info/WHEEL
orchard_lime-0.1.0.dist-info/top_level.txt
orchard_lime-0.1.0.dist-info/RECORD
