Metadata-Version: 2.1
Name: orchard-lime
Version: 0.1.0
Summary: Lime is the MaaS proxy for anonymously access with OpenAI API.
Home-page: https://github.com/OrchardUniverse/lime
Author: Orchard Universe
Classifier: Programming Language :: Python :: 3
Classifier: License :: OSI Approved :: MIT License
Classifier: Operating System :: OS Independent
Requires-Python: >=3.6
License-File: LICENSE
Requires-Dist: fastapi
Requires-Dist: httpx
Requires-Dist: uvicorn
Requires-Dist: pydantic
Requires-Dist: python-dotenv
